{"cameraMode":{"drawMode":0,"name":"Shaded","section":"Shading Mode"},"sceneLighting":false,"audioPlay":false,"sceneViewState":{"showFog":true,"showMaterialUpdate":false,"showSkybox":false,"showFlares":true,"showImageEffects":true,"showParticleSystems":true},"in2DMode":false,"pivot":{"x":-36.101585388183597,"y":-7.538838863372803,"z":5.882387161254883},"rotation":{"x":-0.07615751773118973,"y":0.6478484869003296,"z":-0.06583181768655777,"w":-0.7554318308830261},"size":21.814624786376954,"orthographic":false}